<?xml version="1.0" encoding="UTF-8"?>
<!DOCTYPE suite SYSTEM "https://testng.org/testng-1.0.dtd">
<suite name="Suite">
  <test thread-count="5" name="Test">
    <classes>
      <class name="tESTNGpavanSir.WebHEADLESSclass"/>
      <class name="tESTNGpavanSir.SampleClass"/>
      <class name="tESTNGpavanSir.DataPrividerUSINGexcel"/>
      <class name="tESTNGpavanSir.AnnotationsmethodTest"/>
      <class name="tESTNGpavanSir.DataProviderTest"/>
      <class name="tESTNGpavanSir.DemoClass"/>
      <class name="tESTNGpavanSir.AmazonClass"/>
    </classes>
  </test> <!-- Test -->
</suite> <!-- Suite -->
